keywords2vec/__init__.py
keywords2vec/_nbdev.py
keywords2vec/core.py
keywords2vec/imports.py
keywords2vec/main.py
keywords2vec/tokenizer.py
keywords2vec/utils.py
keywords2vec-0.1.0.dist-info/LICENSE
keywords2vec-0.1.0.dist-info/METADATA
keywords2vec-0.1.0.dist-info/WHEEL
keywords2vec-0.1.0.dist-info/entry_points.txt
keywords2vec-0.1.0.dist-info/top_level.txt
keywords2vec-0.1.0.dist-info/RECORD
