Metadata-Version: 2.1
Name: keywords2vec
Version: 0.1.0
Summary: To generate a word2vec model, but using multi-word keywords instead of single words.
Home-page: https://github.com/dperezrada/keywords2vec
Author: Daniel Pérez Rada
Author-email: dperezrada@gmail.com
License: Apache Software License 2.0
Keywords: word2vec,nlp,text-mining,phrase-extraction,keywords-extraction,multi-language
Platform: UNKNOWN
Classifier: Development Status :: 4 - Beta
Classifier: Intended Audience :: Developers
Classifier: License :: OSI Approved :: Apache Software License
Classifier: Natural Language :: English
Classifier: Programming Language :: Python :: 3.6
Classifier: Programming Language :: Python :: 3.7
Classifier: Programming Language :: Python :: 3.8
Requires-Python: >=3.6
Requires-Dist: nltk
Requires-Dist: Unidecode
Requires-Dist: stop-words
Requires-Dist: fastprogress
Requires-Dist: fasttext
Requires-Dist: annoy
Provides-Extra: dev
Requires-Dist: nbdev ; extra == 'dev'
Requires-Dist: jupyter ; extra == 'dev'
Requires-Dist: ipywidgets ; extra == 'dev'
Requires-Dist: matplotlib ; extra == 'dev'
